docs/Makefile
docs/__init__.py
docs/conf.py
docs/index.rst
docs/make.bat
magen_rest_apis/__init__.py
magen_rest_apis/magen_app.py
magen_rest_apis/magen_urls.py
magen_rest_apis/rest_client_apis.py
magen_rest_apis/rest_exception_apis.py
magen_rest_apis/rest_return_api.py
magen_rest_apis/rest_rfc7807.py
magen_rest_apis/rest_server_apis.py
magen_rest_apis/server_urls.py
magen_rest_service-1.3a10.dist-info/DESCRIPTION.rst
magen_rest_service-1.3a10.dist-info/METADATA
magen_rest_service-1.3a10.dist-info/RECORD
magen_rest_service-1.3a10.dist-info/WHEEL
magen_rest_service-1.3a10.dist-info/metadata.json
magen_rest_service-1.3a10.dist-info/top_level.txt
