Metadata-Version: 2.0
Name: magen-rest-service
Version: 1.3a10
Summary: Magen REST API Package
Home-page: http://www.cisco.com
Author: Reinaldo Penno
Author-email: rapenno@gmail.com
License: Apache
Platform: UNKNOWN
Classifier: Development Status :: 2 - Pre-Alpha
Classifier: Intended Audience :: Education
Classifier: Intended Audience :: Financial and Insurance Industry
Classifier: Intended Audience :: Healthcare Industry
Classifier: Intended Audience :: Legal Industry
Classifier: Topic :: Security
Classifier: License :: OSI Approved :: Apache Software License
Classifier: Programming Language :: Python :: 3.6
Requires-Dist: coverage (>=4.4.1)
Requires-Dist: flake8 (>=3.3.0)
Requires-Dist: Flask (>=0.12.2)
Requires-Dist: pytest (>=3.1.3)
Requires-Dist: requests (>=2.13.0)
Requires-Dist: responses (>=0.8.1)
Requires-Dist: Sphinx (>=1.6.3)
Requires-Dist: wheel (>=0.30.0a0)
Requires-Dist: magen-logger (>=1.0a)
Requires-Dist: magen-utils (>=1.2a)
